pi_optimal/__init__.py
pi_optimal/agents/agent.py
pi_optimal/datasets/__init__.py
pi_optimal/datasets/base_dataset.py
pi_optimal/datasets/timeseries_dataset.py
pi_optimal/datasets/utils/__init__.py
pi_optimal/datasets/utils/processors.py
pi_optimal/evaluators/base_evaluator.py
pi_optimal/evaluators/plotting.py
pi_optimal/models/base_model.py
pi_optimal/models/sklearn/base_sklearn_model.py
pi_optimal/models/sklearn/hybrid_model.py
pi_optimal/models/sklearn/linear_model.py
pi_optimal/models/sklearn/mlp.py
pi_optimal/models/sklearn/random_forest_model.py
pi_optimal/models/sklearn/svm.py
pi_optimal/planners/base_planner.py
pi_optimal/planners/cem_continuous.py
pi_optimal/planners/cem_discrete.py
pi_optimal/planners/cem_planner.py
pi_optimal/utils/__init__.py
pi_optimal/utils/data_generators/base_data_generator.py
pi_optimal/utils/data_generators/gym_data_generator.py
pi_optimal/utils/logger.py
pi_optimal/utils/serialization.py
pi_optimal/utils/trajectory_visualizer.py
pi_optimal/utils/validation.py
pi_optimal-0.1.4.dist-info/LICENSE
pi_optimal-0.1.4.dist-info/METADATA
pi_optimal-0.1.4.dist-info/WHEEL
pi_optimal-0.1.4.dist-info/RECORD
