Metadata-Version: 2.3
Name: pi-optimal
Version: 0.1.4
Summary: Python package for easy, data-efficient RL-based decision-making in business applications.
License: AGPL-3.0-or-later
Keywords: rl,decision intelligence,reinforcement learning,decision-making,pi,optimal
Author: pi-optimal UG (haftungsbeschränkt)
Author-email: hello@pi-optimal.com
Maintainer: Jochen Luithardt
Maintainer-email: jol@pi-optimal.com
Requires-Python: >=3.10,<4.0
Classifier: License :: OSI Approved :: GNU Affero General Public License v3 or later (AGPLv3+)
Classifier: Programming Language :: Python :: 3
Classifier: Programming Language :: Python :: 3.10
Classifier: Programming Language :: Python :: 3.11
Classifier: Programming Language :: Python :: 3.12
Classifier: Programming Language :: Python :: 3.13
Provides-Extra: notebook
Requires-Dist: gymnasium[box2d] (>=1.0.0,<2.0.0)
Requires-Dist: ipykernel (>=6.29.5,<7.0.0) ; extra == "notebook"
Requires-Dist: ipysheet (>=0.7.0,<0.8.0)
Requires-Dist: ipywidgets (>=8.1.5,<9.0.0)
Requires-Dist: jupyter (>=1.0.0,<2.0.0) ; extra == "notebook"
Requires-Dist: matplotlib (>=3.9.1.post1,<4.0.0)
Requires-Dist: nbformat (>=5.10.4,<6.0.0)
Requires-Dist: numpy (>=1.25.0,<2.0.0)
Requires-Dist: pandas (>=2.2.2,<3.0.0)
Requires-Dist: plotly (>=5.24.1,<6.0.0)
Requires-Dist: scikit-learn (>=1.5.1,<2.0.0)
Requires-Dist: swig (>=4.3.0,<5.0.0)
Requires-Dist: torch (>=2.3,<3.0)
Requires-Dist: tqdm (>=4.66.4,<5.0.0)
Project-URL: documentation, https://pi-optimal.com/docs/getting-started
Project-URL: homepage, https://pi-optimal.com/
Project-URL: repository, https://github.com/pi-optimal/pi-optimal
